LICENSE
MANIFEST.in
README.md
setup.py
tox.ini
django_reamaze/__init__.py
django_reamaze/models.py
django_reamaze/test_settings.py
django_reamaze/tests.py
django_reamaze/urls.py
django_reamaze/views.py
django_reamaze.egg-info/PKG-INFO
django_reamaze.egg-info/SOURCES.txt
django_reamaze.egg-info/dependency_links.txt
django_reamaze.egg-info/not-zip-safe
django_reamaze.egg-info/pbr.json
django_reamaze.egg-info/top_level.txt
django_reamaze/templates/django_reamaze/templatetags/reamaze.html
django_reamaze/templatetags/__init__.py
django_reamaze/templatetags/reamaze.py