Metadata-Version: 1.1
Name: django-reamaze
Version: 0.6
Summary: A simple App for connect Django and Reamaze
Home-page: https://github.com/mrjmad/django-reamaze
Author: Jean-Michel ARMAND
Author-email: j-mad@j-mad.com
License: MIT License
Platform: UNKNOWN
Classifier: Environment :: Web Environment
Classifier: Framework :: Django
Classifier: Intended Audience :: Developers
Classifier: License :: OSI Approved :: MIT License
Classifier: Operating System :: OS Independent
Classifier: Programming Language :: Python
Classifier: Programming Language :: Python :: 2
Classifier: Programming Language :: Python :: 2.7
Classifier: Topic :: Internet :: WWW/HTTP
Classifier: Topic :: Internet :: WWW/HTTP :: Dynamic Content
